{
  "type": "footer",
  "name": "Footer group",
  "sections": {
    "theme_footer": {
      "type": "theme__footer",
      "blocks": {
        "78204a1a-1009-4f50-a9c8-4a9f0b2af321": {
          "type": "newsletter",
          "settings": {
            "heading": "Newsletter",
            "content": "<p>Tell customers why they should subscribe to your newsletter.<\/p>",
            "button": "Subscribe",
            "disclaimer": "<p>Include an additional disclaimer to clarify how you will use a subscribers email.<\/p>",
            "success": "<p>Success! You’ve been subscribed.<\/p>"
          }
        },
        "5dc22179-9717-40d2-9d83-4532c904e6d1": {
          "type": "menu",
          "settings": {
            "menu": ""
          }
        },
        "150805eb-9862-49dd-b0c2-0111162d6fce": {
          "type": "menu",
          "settings": {
            "menu": "footer"
          }
        },
        "6ad6b950-210d-4cf8-b231-62c67db4980e": {
          "type": "menu",
          "settings": {
            "menu": "footer"
          }
        }
      },
      "block_order": [
        "78204a1a-1009-4f50-a9c8-4a9f0b2af321",
        "5dc22179-9717-40d2-9d83-4532c904e6d1",
        "150805eb-9862-49dd-b0c2-0111162d6fce",
        "6ad6b950-210d-4cf8-b231-62c67db4980e"
      ],
      "settings": {
        "main_color_scheme": "color__bg-secondary color__secondary",
        "main_color_border": "!color__border-transparent",
        "main_color_button": "btn btn--secondary",
        "sub_color_scheme": "color__bg-secondary color__secondary",
        "sub_color_border": "color__border-selected-1",
        "sub_color_button": "btn btn--secondary",
        "sub_links": "footer",
        "sub_enable_payment_icons": true,
        "visibility": ""
      }
    }
  },
  "order": [
    "theme_footer"
  ]
}